ramsey/ramsey.py
zangorth_ramsey-1.1.5.dist-info/METADATA
zangorth_ramsey-1.1.5.dist-info/WHEEL
zangorth_ramsey-1.1.5.dist-info/top_level.txt
zangorth_ramsey-1.1.5.dist-info/RECORD
